{
  "tag": "2021-09-26_115034",
  "state_str": "a8be3522f75e663b83ea6eec0853557b",
  "state_str_content_free": "6c876bbc7094c18f32ae3dd874d22c62",
  "foreground_activity": "com.example.ujsAutoClock/.MainActivity",
  "activity_stack": [
    "com.example.ujsAutoClock/.MainActivity"
  ],
  "background_services": [
    "com.google.android.gms/.chimera.PersistentInternalBoundBrokerService",
    "com.google.android.networkstack.tethering/com.android.networkstack.tethering.TetheringService",
    "com.google.android.gms/.auth.frp.FrpService",
    "com.google.android.gms/.nearby.sharing.ReceiveSurfaceService",
    "com.google.android.gms/.chimera.GmsInternalApiService",
    "com.google.android.gms/.icing.service.AppIndexingService",
    "com.google.android.gms/.deviceconnection.service.DeviceConnectionWatcherService",
    "com.android.systemui/.keyguard.KeyguardService",
    "com.android.bluetooth/.btservice.AdapterService",
    "com.google.android.gms/.instantapps.service.InstantAppsService",
    "com.android.systemui/.ImageWallpaper",
    "com.google.android.gms/com.google.android.location.geocode.GeocodeService",
    "com.google.android.gms/.auth.setup.devicesignals.LockScreenService",
    "com.google.android.gms/.gcm.GcmService",
    "com.google.android.gms/.auth.proximity.firstparty.SystemMemoryCacheService",
    "com.google.android.gms/.chimera.PersistentApiService",
    "com.android.phone/com.android.internal.telephony.CellularNetworkService",
    "com.google.android.gms/com.google.location.nearby.direct.service.NearbyDirectService",
    "com.google.android.gms/.chimera.PersistentBoundBrokerService",
    "com.android.bluetooth/.gatt.GattService",
    "com.google.android.gms/.chimera.GmsBoundBrokerService",
    "com.google.android.gms/.chimera.GmsApiService",
    "com.google.android.gms/.fido.fido2.pollux.CableAuthenticatorService",
    "com.google.android.googlequicksearchbox/com.google.android.apps.gsa.nowoverlayservice.DrawerOverlayService",
    "io.github.ylimit.droidbotapp/.DroidBotIME",
    "com.android.bluetooth/.pbap.BluetoothPbapService",
    "com.google.android.gms/com.google.android.location.fused.FusedLocationService",
    "com.google.android.inputmethod.latin/com.google.android.libraries.micore.training.cache.service.TrainingCacheManagerService",
    "com.google.android.gms/.gcm.nts.SchedulerService",
    "com.google.android.ext.services/android.ext.services.autofill.InlineSuggestionRenderServiceImpl",
    "com.android.bluetooth/.a2dp.A2dpService",
    "com.google.android.providers.media.module/com.android.providers.media.fuse.ExternalStorageServiceImpl",
    "io.github.ylimit.droidbotapp/io.github.privacystreams.accessibility.PSAccessibilityService",
    "com.google.android.gms/.thunderbird.EmergencyPersistentService",
    "com.google.android.apps.nexuslauncher/com.android.launcher3.notification.NotificationListener",
    "com.android.systemui/.SystemUIService",
    "com.google.android.gms/.nearby.exposurenotification.service.ExposureMatchingService",
    "android/.hardware.location.GeofenceHardwareService",
    "com.android.se/.SecureElementService",
    "com.google.android.gms/.presencemanager.service.PresenceManagerPresenceReportService",
    "com.google.android.ims/.services.RcsService",
    "com.google.android.gms/.chimera.GmsIntentOperationService",
    "com.google.android.gms/.chimera.PersistentDirectBootAwareApiService",
    "com.android.bluetooth/.hid.HidDeviceService",
    "com.google.android.ext.services/android.ext.services.notification.Assistant",
    "com.google.android.gms/.location.persistent.LocationPersistentService",
    "com.google.android.gms/.nearby.discovery.service.DiscoveryService",
    "com.google.android.gms/com.google.android.location.internal.PendingIntentCallbackService",
    "com.google.android.gms/.nearby.messages.service.NearbyMessagesService",
    "com.android.server.telecom/.components.BluetoothPhoneService",
    "com.google.android.gms/com.google.android.location.internal.server.GoogleLocationService",
    "com.google.android.gms/com.google.android.contextmanager.service.ContextManagerService",
    "com.android.systemui/.dump.SystemUIAuxiliaryDumpService",
    "com.google.android.gms/com.google.android.location.network.NetworkLocationService",
    "com.android.stk/.StkAppService",
    "com.google.android.gms/com.google.android.location.internal.GoogleLocationManagerService",
    "com.android.phone/com.android.internal.telephony.dataconnection.CellularDataService",
    "com.android.service.ims/.RcsService",
    "com.android.server.telecom/.components.TelecomService",
    "com.google.android.networkstack/com.android.server.NetworkStackService",
    "com.android.bluetooth/.hfp.HeadsetService",
    "com.google.android.googlequicksearchbox/com.google.android.voiceinteraction.GsaVoiceInteractionService",
    "com.android.emulator.multidisplay/.MultiDisplayService",
    "com.android.phone/.vvm.RemoteVvmTaskManager",
    "com.google.android.gms/.lockbox.service.LockboxBrokerService",
    "com.android.ons/.OpportunisticNetworkService",
    "com.google.android.apps.messaging/.shared.datamodel.action.execution.ActionExecutorImpl",
    "com.google.android.gms/.common.stats.GmsCoreStatsService",
    "com.google.android.gms/.nearby.exposurenotification.WakeUpService",
    "com.google.android.gms/com.google.android.location.internal.server.HardwareArProviderService",
    "com.android.bluetooth/.map.BluetoothMapService",
    "com.android.phone/com.android.services.telephony.sip.components.TelephonySipService",
    "com.android.phone/.TelephonyDebugService",
    "com.android.bluetooth/.hid.HidHostService",
    "com.google.android.gms/.icing.service.IndexService",
    "com.android.bluetooth/.opp.BluetoothOppService",
    "com.android.bluetooth/.pan.PanService",
    "com.android.bluetooth/.avrcp.AvrcpTargetService",
    "com.google.android.apps.nexuslauncher/com.android.quickstep.TouchInteractionService",
    "com.google.android.cellbroadcastservice/com.android.cellbroadcastservice.DefaultCellBroadcastService",
    "com.google.android.gms/.checkin.CheckinApiService",
    "com.google.android.setupwizard/.deferred.DeferredSetupScheduler",
    "com.google.android.setupwizard/.predeferred.PreDeferredServiceScheduler"
  ],
  "width": 1080,
  "height": 1920,
  "views": [
    {
      "package": "com.example.ujsAutoClock",
      "visible": true,
      "checkable": false,
      "child_count": 1,
      "editable": false,
      "clickable": false,
      "is_password": false,
      "focusable": false,
      "enabled": true,
      "content_description": null,
      "children": [
        1
      ],
      "focused": false,
      "bounds": [
        [
          555,
          74
        ],
        [
          1070,
          494
        ]
      ],
      "resource_id": null,
      "checked": false,
      "text": null,
      "class": "android.widget.FrameLayout",
      "scrollable": false,
      "selected": false,
      "long_clickable": false,
      "parent": -1,
      "temp_id": 0,
      "size": "515*420",
      "signature": "[class]android.widget.FrameLayout[resource_id]None[text]None[enabled,,]",
      "view_str": "08e0c27377beb4dc343382e1248e73d2",
      "content_free_signature": "[class]android.widget.FrameLayout[resource_id]None"
    },
    {
      "package": "com.example.ujsAutoClock",
      "visible": true,
      "checkable": false,
      "child_count": 1,
      "editable": false,
      "clickable": false,
      "is_password": false,
      "focusable": false,
      "enabled": true,
      "content_description": null,
      "children": [
        2
      ],
      "focused": false,
      "bounds": [
        [
          555,
          74
        ],
        [
          1070,
          494
        ]
      ],
      "resource_id": null,
      "checked": false,
      "text": null,
      "class": "android.widget.FrameLayout",
      "scrollable": false,
      "selected": false,
      "long_clickable": false,
      "parent": 0,
      "temp_id": 1,
      "size": "515*420",
      "signature": "[class]android.widget.FrameLayout[resource_id]None[text]None[enabled,,]",
      "view_str": "40aec82867d01ba79366f85ea0a39dcd",
      "content_free_signature": "[class]android.widget.FrameLayout[resource_id]None"
    },
    {
      "package": "com.example.ujsAutoClock",
      "visible": true,
      "checkable": false,
      "child_count": 3,
      "editable": false,
      "clickable": false,
      "is_password": false,
      "focusable": true,
      "enabled": true,
      "content_description": null,
      "children": [
        3,
        7,
        11
      ],
      "focused": false,
      "bounds": [
        [
          555,
          95
        ],
        [
          1070,
          473
        ]
      ],
      "resource_id": null,
      "checked": false,
      "text": null,
      "class": "android.widget.ListView",
      "scrollable": false,
      "selected": false,
      "long_clickable": false,
      "parent": 1,
      "temp_id": 2,
      "size": "515*378",
      "signature": "[class]android.widget.ListView[resource_id]None[text]None[enabled,,]",
      "view_str": "4a73f62c3572aa2b3e76882e85fad95f",
      "content_free_signature": "[class]android.widget.ListView[resource_id]None"
    },
    {
      "package": "com.example.ujsAutoClock",
      "visible": true,
      "checkable": false,
      "child_count": 1,
      "editable": false,
      "clickable": true,
      "is_password": false,
      "focusable": false,
      "enabled": true,
      "content_description": null,
      "children": [
        4
      ],
      "focused": false,
      "bounds": [
        [
          555,
          95
        ],
        [
          1070,
          221
        ]
      ],
      "resource_id": null,
      "checked": false,
      "text": null,
      "class": "android.widget.LinearLayout",
      "scrollable": false,
      "selected": false,
      "long_clickable": false,
      "parent": 2,
      "temp_id": 3,
      "size": "515*126",
      "signature": "[class]android.widget.LinearLayout[resource_id]None[text]None[enabled,,]",
      "view_str": "cfb57db5c5d56e69b962dc90640e2ed0",
      "content_free_signature": "[class]android.widget.LinearLayout[resource_id]None"
    },
    {
      "package": "com.example.ujsAutoClock",
      "visible": true,
      "checkable": false,
      "child_count": 1,
      "editable": false,
      "clickable": false,
      "is_password": false,
      "focusable": false,
      "enabled": true,
      "content_description": null,
      "children": [
        5
      ],
      "focused": false,
      "bounds": [
        [
          555,
          95
        ],
        [
          1070,
          221
        ]
      ],
      "resource_id": "com.example.ujsAutoClock:id/content",
      "checked": false,
      "text": null,
      "class": "android.widget.LinearLayout",
      "scrollable": false,
      "selected": false,
      "long_clickable": false,
      "parent": 3,
      "temp_id": 4,
      "size": "515*126",
      "signature": "[class]android.widget.LinearLayout[resource_id]com.example.ujsAutoClock:id/content[text]None[enabled,,]",
      "view_str": "8cc483119b7776326a9c6f97993e2e4f",
      "content_free_signature": "[class]android.widget.LinearLayout[resource_id]com.example.ujsAutoClock:id/content"
    },
    {
      "package": "com.example.ujsAutoClock",
      "visible": true,
      "checkable": false,
      "child_count": 1,
      "editable": false,
      "clickable": false,
      "is_password": false,
      "focusable": false,
      "enabled": true,
      "content_description": null,
      "children": [
        6
      ],
      "focused": false,
      "bounds": [
        [
          597,
          129
        ],
        [
          1028,
          186
        ]
      ],
      "resource_id": null,
      "checked": false,
      "text": null,
      "class": "android.widget.RelativeLayout",
      "scrollable": false,
      "selected": false,
      "long_clickable": false,
      "parent": 4,
      "temp_id": 5,
      "size": "431*57",
      "signature": "[class]android.widget.RelativeLayout[resource_id]None[text]None[enabled,,]",
      "view_str": "7a1398ee6d677bb29ee17b9030769732",
      "content_free_signature": "[class]android.widget.RelativeLayout[resource_id]None"
    },
    {
      "package": "com.example.ujsAutoClock",
      "visible": true,
      "checkable": false,
      "child_count": 0,
      "editable": false,
      "clickable": false,
      "is_password": false,
      "focusable": false,
      "enabled": true,
      "content_description": null,
      "children": [],
      "focused": false,
      "bounds": [
        [
          597,
          129
        ],
        [
          1028,
          186
        ]
      ],
      "resource_id": "com.example.ujsAutoClock:id/title",
      "checked": false,
      "text": "\u6253\u5f00APP\u8bbe\u7f6e",
      "class": "android.widget.TextView",
      "scrollable": false,
      "selected": false,
      "long_clickable": false,
      "parent": 5,
      "temp_id": 6,
      "size": "431*57",
      "signature": "[class]android.widget.TextView[resource_id]com.example.ujsAutoClock:id/title[text]\u6253\u5f00APP\u8bbe\u7f6e[enabled,,]",
      "view_str": "091b722318477088fe07b157918b9147",
      "content_free_signature": "[class]android.widget.TextView[resource_id]com.example.ujsAutoClock:id/title"
    },
    {
      "package": "com.example.ujsAutoClock",
      "visible": true,
      "checkable": false,
      "child_count": 1,
      "editable": false,
      "clickable": true,
      "is_password": false,
      "focusable": false,
      "enabled": true,
      "content_description": null,
      "children": [
        8
      ],
      "focused": false,
      "bounds": [
        [
          555,
          221
        ],
        [
          1070,
          347
        ]
      ],
      "resource_id": null,
      "checked": false,
      "text": null,
      "class": "android.widget.LinearLayout",
      "scrollable": false,
      "selected": false,
      "long_clickable": false,
      "parent": 2,
      "temp_id": 7,
      "size": "515*126",
      "signature": "[class]android.widget.LinearLayout[resource_id]None[text]None[enabled,,]",
      "view_str": "cfb57db5c5d56e69b962dc90640e2ed0",
      "content_free_signature": "[class]android.widget.LinearLayout[resource_id]None"
    },
    {
      "package": "com.example.ujsAutoClock",
      "visible": true,
      "checkable": false,
      "child_count": 1,
      "editable": false,
      "clickable": false,
      "is_password": false,
      "focusable": false,
      "enabled": true,
      "content_description": null,
      "children": [
        9
      ],
      "focused": false,
      "bounds": [
        [
          555,
          221
        ],
        [
          1070,
          347
        ]
      ],
      "resource_id": "com.example.ujsAutoClock:id/content",
      "checked": false,
      "text": null,
      "class": "android.widget.LinearLayout",
      "scrollable": false,
      "selected": false,
      "long_clickable": false,
      "parent": 7,
      "temp_id": 8,
      "size": "515*126",
      "signature": "[class]android.widget.LinearLayout[resource_id]com.example.ujsAutoClock:id/content[text]None[enabled,,]",
      "view_str": "8cc483119b7776326a9c6f97993e2e4f",
      "content_free_signature": "[class]android.widget.LinearLayout[resource_id]com.example.ujsAutoClock:id/content"
    },
    {
      "package": "com.example.ujsAutoClock",
      "visible": true,
      "checkable": false,
      "child_count": 1,
      "editable": false,
      "clickable": false,
      "is_password": false,
      "focusable": false,
      "enabled": true,
      "content_description": null,
      "children": [
        10
      ],
      "focused": false,
      "bounds": [
        [
          597,
          255
        ],
        [
          1028,
          312
        ]
      ],
      "resource_id": null,
      "checked": false,
      "text": null,
      "class": "android.widget.RelativeLayout",
      "scrollable": false,
      "selected": false,
      "long_clickable": false,
      "parent": 8,
      "temp_id": 9,
      "size": "431*57",
      "signature": "[class]android.widget.RelativeLayout[resource_id]None[text]None[enabled,,]",
      "view_str": "a0b435131fff735d3216e5ba8bab97ed",
      "content_free_signature": "[class]android.widget.RelativeLayout[resource_id]None"
    },
    {
      "package": "com.example.ujsAutoClock",
      "visible": true,
      "checkable": false,
      "child_count": 0,
      "editable": false,
      "clickable": false,
      "is_password": false,
      "focusable": false,
      "enabled": true,
      "content_description": null,
      "children": [],
      "focused": false,
      "bounds": [
        [
          597,
          255
        ],
        [
          1028,
          312
        ]
      ],
      "resource_id": "com.example.ujsAutoClock:id/title",
      "checked": false,
      "text": "\u6253\u5f00\u81ea\u542f\u52a8\u8bbe\u7f6e",
      "class": "android.widget.TextView",
      "scrollable": false,
      "selected": false,
      "long_clickable": false,
      "parent": 9,
      "temp_id": 10,
      "size": "431*57",
      "signature": "[class]android.widget.TextView[resource_id]com.example.ujsAutoClock:id/title[text]\u6253\u5f00\u81ea\u542f\u52a8\u8bbe\u7f6e[enabled,,]",
      "view_str": "160072c2a87b8bdfaf5ca2496b2a979a",
      "content_free_signature": "[class]android.widget.TextView[resource_id]com.example.ujsAutoClock:id/title"
    },
    {
      "package": "com.example.ujsAutoClock",
      "visible": true,
      "checkable": false,
      "child_count": 1,
      "editable": false,
      "clickable": true,
      "is_password": false,
      "focusable": false,
      "enabled": true,
      "content_description": null,
      "children": [
        12
      ],
      "focused": false,
      "bounds": [
        [
          555,
          347
        ],
        [
          1070,
          473
        ]
      ],
      "resource_id": null,
      "checked": false,
      "text": null,
      "class": "android.widget.LinearLayout",
      "scrollable": false,
      "selected": false,
      "long_clickable": false,
      "parent": 2,
      "temp_id": 11,
      "size": "515*126",
      "signature": "[class]android.widget.LinearLayout[resource_id]None[text]None[enabled,,]",
      "view_str": "cfb57db5c5d56e69b962dc90640e2ed0",
      "content_free_signature": "[class]android.widget.LinearLayout[resource_id]None"
    },
    {
      "package": "com.example.ujsAutoClock",
      "visible": true,
      "checkable": false,
      "child_count": 1,
      "editable": false,
      "clickable": false,
      "is_password": false,
      "focusable": false,
      "enabled": true,
      "content_description": null,
      "children": [
        13
      ],
      "focused": false,
      "bounds": [
        [
          555,
          347
        ],
        [
          1070,
          473
        ]
      ],
      "resource_id": "com.example.ujsAutoClock:id/content",
      "checked": false,
      "text": null,
      "class": "android.widget.LinearLayout",
      "scrollable": false,
      "selected": false,
      "long_clickable": false,
      "parent": 11,
      "temp_id": 12,
      "size": "515*126",
      "signature": "[class]android.widget.LinearLayout[resource_id]com.example.ujsAutoClock:id/content[text]None[enabled,,]",
      "view_str": "8cc483119b7776326a9c6f97993e2e4f",
      "content_free_signature": "[class]android.widget.LinearLayout[resource_id]com.example.ujsAutoClock:id/content"
    },
    {
      "package": "com.example.ujsAutoClock",
      "visible": true,
      "checkable": false,
      "child_count": 1,
      "editable": false,
      "clickable": false,
      "is_password": false,
      "focusable": false,
      "enabled": true,
      "content_description": null,
      "children": [
        14
      ],
      "focused": false,
      "bounds": [
        [
          597,
          381
        ],
        [
          1028,
          438
        ]
      ],
      "resource_id": null,
      "checked": false,
      "text": null,
      "class": "android.widget.RelativeLayout",
      "scrollable": false,
      "selected": false,
      "long_clickable": false,
      "parent": 12,
      "temp_id": 13,
      "size": "431*57",
      "signature": "[class]android.widget.RelativeLayout[resource_id]None[text]None[enabled,,]",
      "view_str": "e6048299e9b071bca56ac3fb906d6f9c",
      "content_free_signature": "[class]android.widget.RelativeLayout[resource_id]None"
    },
    {
      "package": "com.example.ujsAutoClock",
      "visible": true,
      "checkable": false,
      "child_count": 0,
      "editable": false,
      "clickable": false,
      "is_password": false,
      "focusable": false,
      "enabled": true,
      "content_description": null,
      "children": [],
      "focused": false,
      "bounds": [
        [
          597,
          381
        ],
        [
          1028,
          438
        ]
      ],
      "resource_id": "com.example.ujsAutoClock:id/title",
      "checked": false,
      "text": "\u67e5\u770b\u6700\u8fd1\u81ea\u52a8\u6253\u5361\u8bb0\u5f55",
      "class": "android.widget.TextView",
      "scrollable": false,
      "selected": false,
      "long_clickable": false,
      "parent": 13,
      "temp_id": 14,
      "size": "431*57",
      "signature": "[class]android.widget.TextView[resource_id]com.example.ujsAutoClock:id/title[text]\u67e5\u770b\u6700\u8fd1\u81ea\u52a8\u6253\u5361\u8bb0\u5f55[enabled,,]",
      "view_str": "63697bf676f2a935460df0a7d1b60057",
      "content_free_signature": "[class]android.widget.TextView[resource_id]com.example.ujsAutoClock:id/title"
    }
  ]
}